[
  {
    "Name": "Shadow Defender",
    "Type": "yandex",
    "DownloadUrl": "https://disk.yandex.ru/d/t4OQ6EaJUtKHOQ",
    "Arguments": [
      "/S",
      "/RU",
      "/NS",
      "/ND"
    ]
  },
  {
    "Name": "Revo Uninstaller Pro",
    "Type": "yandex",
    "DownloadUrl": "https://disk.yandex.ru/d/04cpGnYo1pSVHw",
    "Arguments": [
      "/S",
      "/I"
    ]
  },
  {
    "Name": "Driver Booster",
    "Type": "direct",
    "DownloadUrl": "https://cdn.iobit.com/insurweb/dl_ruseo_dbfpdp/driver_booster_setup.exe",
    "Arguments": [
      "/VERYSILENT",
      "/NORESTART"
    ]
  },
  {
    "Name": "Google Chrome",
    "Type": "direct",
    "DownloadUrl": "https://dl.google.com/chrome/install/GoogleChromeStandaloneEnterprise64.msi",
    "Arguments": [
      "/quiet",
      "/passive",
      "/norestart",
      "/qn"
    ]
  },
  {
    "Name": "Veyon",
    "Type": "direct",
    "PageUrl": "https://veyon.io/en/download/",
    "FilterMode": "Like",
    "Pattern": "*win64-setup.exe",
    "Index": 1,
    "Arguments": [
      "/S",
      "/NoMaster"
    ]
  },
  {
    "Name": "Roblox Studio",
    "Type": "direct",
    "DownloadUrl": "https://setup.rbxcdn.com/RobloxStudioInstaller.exe"
  },
  {
    "Name": "AlgoVsCode",
    "Type": "yandex",
    "DownloadUrl": "https://disk.360.yandex.ru/d/r40brL-Y6dk7YA",
    "Arguments": [
      "/VERYSILENT",
      "/NORESTART"
    ]
  },
  {
    "Name": "VsCode",
    "Type": "yandex",
    "DownloadUrl": "https://disk.yandex.ru/d/Ou-ANS_yEsHLng",
    "Arguments": [
      "/VERYSILENT",
      "/NORESTART"
    ]
  },
  {
    "Name": "GIMP",
    "Type": "direct",
    "DownloadUrl": "https://download.gimp.org/gimp/v3.0/windows/gimp-3.0.6-setup-1.exe",
    "Arguments": [
      "/VERYSILENT",
      "/NORESTART",
      "/ALLUSERS"
    ]
  },
  {
    "Name": "Python",
    "Type": "Direct",
    "PageUrl": "https://www.python.org/downloads/",
    "FilterMode": "Like",
    "Pattern": "*amd64.exe",
    "Index": 1,
    "Arguments": [
      "/quite",
      "/passive",
      "InstallAllUsers=1",
      "CompileAll=1",
      "AppendPath=1",
      "Shortcuts=0",
      "Include_doc=0",
      "Include_debug=1",
      "Include_launcher=0",
      "Include_symbols=1"
    ]
  },
  {
    "Name": "OpenShot",
    "Type": "direct",
    "PageUrl": "https://www.openshot.org/download/",
    "FilterMode": "Like",
    "Pattern": "*.exe",
    "Index": 1,
    "Arguments": [
      "/VERYSILENT",
      "/NORESTART",
      "/ALLUSERS"
    ]
  },
  {
    "Name": "Twine",
    "Type": "github",
    "RepositoryAuthor": "klembot",
    "RepositoryName": "twinejs",
    "AssetFilterMode": "Match",
    "AssetPattern": "Windows.exe",
    "Arguments": [
      "/allusers",
      "/S"
    ]
  },
  {
    "Name": "Blender",
    "Type": "direct",
    "DownloadUrl": "https://download.blender.org/release/Blender5.0/blender-5.0.1-windows-x64.msi",
    "Arguments": [
      "/quiet",
      "/passive",
      "/norestart",
      "/qn"
    ]
  },
  {
    "Name": "Scribus",
    "Type": "sourceforge",
    "Repository": "scribus",
    "Arguments": [
      "/S"
    ]
  },
  {
    "Name": "Inkscape",
    "Type": "direct",
    "DownloadUrl": "https://media.inkscape.org/dl/resources/file/inkscape-1.4.3.msi",
    "Arguments": [
      "/quiet",
      "/passive",
      "/norestart",
      "/qn"
    ]
  },
  {
    "Name": "Tile Setter",
    "Type": "yandex",
    "DownloadUrl": "https://disk.yandex.ru/d/vXBg8eJstg7uvw"
  },
  {
    "Name": "RPG Paper Maker",
    "Type": "direct",
    "PageUrl": "https://rpg-paper-maker.com/downloads/",
    "FilterMode": "Like",
    "Pattern": "*.exe",
    "Index": 1,
    "Arguments": [
      "/VERYSILENT",
      "/NORESTART"
    ]
  }
]
